tisseglibrary/__init__.py
tisseglibrary/tisseglibrary.py
tisseglibrary-0.1.4.dist-info/METADATA
tisseglibrary-0.1.4.dist-info/WHEEL
tisseglibrary-0.1.4.dist-info/licenses/LICENSE
tisseglibrary-0.1.4.dist-info/licenses/LICENSE.txt
tisseglibrary-0.1.4.dist-info/RECORD
