Metadata-Version: 2.1
Name: TisSegLibrary
Version: 0.1.4
Summary: It gets the 2D/3D segmentation of the abdomen and the thigh
Project-URL: Homepage, https://github.com/MarinaSandonis/TisSegLibrary
Project-URL: Bug Tracker, https://github.com/MarinaSandonis/TisSegLibrary/issues
Author-email: Marina Sandonis <marinasandfer@gmail.com>
License:  Apache License
Classifier: License :: OSI Approved :: MIT License
Classifier: Operating System :: OS Independent
Classifier: Programming Language :: Python :: 3
Requires-Python: >=2.7
